yowasp_nextpnr_machxo2/__init__.py
yowasp_nextpnr_machxo2/ecpbram.wasm
yowasp_nextpnr_machxo2/ecpmulti.wasm
yowasp_nextpnr_machxo2/ecppack.wasm
yowasp_nextpnr_machxo2/ecppll.wasm
yowasp_nextpnr_machxo2/ecpunpack.wasm
yowasp_nextpnr_machxo2/nextpnr-machxo2.wasm
yowasp_nextpnr_machxo2/share/machxo2/chipdb-1200.bin
yowasp_nextpnr_machxo2/share/machxo2/chipdb-6900.bin
yowasp_nextpnr_machxo2/share/trellis/database/devices.json
yowasp_nextpnr_machxo2/share/trellis/database/MachXO2/LCMXO2-1200/iodb.json
yowasp_nextpnr_machxo2/share/trellis/database/MachXO2/LCMXO2-1200/tilegrid.json
yowasp_nextpnr_machxo2/share/trellis/database/MachXO2/LCMXO2-2000/iodb.json
yowasp_nextpnr_machxo2/share/trellis/database/MachXO2/LCMXO2-2000/tilegrid.json
yowasp_nextpnr_machxo2/share/trellis/database/MachXO2/LCMXO2-256/iodb.json
yowasp_nextpnr_machxo2/share/trellis/database/MachXO2/LCMXO2-256/tilegrid.json
yowasp_nextpnr_machxo2/share/trellis/database/MachXO2/LCMXO2-4000/iodb.json
yowasp_nextpnr_machxo2/share/trellis/database/MachXO2/LCMXO2-4000/tilegrid.json
yowasp_nextpnr_machxo2/share/trellis/database/MachXO2/LCMXO2-640/iodb.json
yowasp_nextpnr_machxo2/share/trellis/database/MachXO2/LCMXO2-640/tilegrid.json
yowasp_nextpnr_machxo2/share/trellis/database/MachXO2/LCMXO2-7000/iodb.json
yowasp_nextpnr_machxo2/share/trellis/database/MachXO2/LCMXO2-7000/tilegrid.json
yowasp_nextpnr_machxo2/share/trellis/database/MachXO2/tiledata/B_DUMMY_ENDL/bits.db
yowasp_nextpnr_machxo2/share/trellis/database/MachXO2/tiledata/B_DUMMY_ENDR/bits.db
yowasp_nextpnr_machxo2/share/trellis/database/MachXO2/tiledata/B_DUMMY_ENDR_VREF2/bits.db
yowasp_nextpnr_machxo2/share/trellis/database/MachXO2/tiledata/CENTER0/bits.db
yowasp_nextpnr_machxo2/share/trellis/database/MachXO2/tiledata/CENTER1/bits.db
yowasp_nextpnr_machxo2/share/trellis/database/MachXO2/tiledata/CENTER2/bits.db
yowasp_nextpnr_machxo2/share/trellis/database/MachXO2/tiledata/CENTER3/bits.db
yowasp_nextpnr_machxo2-0.9.0.0.post686.dist-info/METADATA
yowasp_nextpnr_machxo2-0.9.0.0.post686.dist-info/WHEEL
yowasp_nextpnr_machxo2-0.9.0.0.post686.dist-info/entry_points.txt
yowasp_nextpnr_machxo2-0.9.0.0.post686.dist-info/top_level.txt
yowasp_nextpnr_machxo2-0.9.0.0.post686.dist-info/RECORD
